my_module/__init__.py
my_module/data_params.py
my_module/dataset.py
my_module/inference.py
my_module/train.py
homework5-0.1.0.dist-info/METADATA
homework5-0.1.0.dist-info/WHEEL
homework5-0.1.0.dist-info/top_level.txt
homework5-0.1.0.dist-info/RECORD
