Metadata-Version: 2.1
Name: homework5
Version: 0.1.0
Summary: MLPOPS
Author: Mariiiiiiiia
License: MIT
